decloud_creator/__init__.py
decloud_creator/cli.py
decloud_creator/config.py
decloud_creator/creator.py
decloud_creator/ipfs.py
decloud_creator/storage.py
decloud_creator_kit-0.1.0.dist-info/METADATA
decloud_creator_kit-0.1.0.dist-info/WHEEL
decloud_creator_kit-0.1.0.dist-info/entry_points.txt
decloud_creator_kit-0.1.0.dist-info/top_level.txt
decloud_creator_kit-0.1.0.dist-info/RECORD
