Metadata-Version: 2.4
Name: decloud-creator-kit
Version: 0.1.0
Summary: DECLOUD Creator Kit - Create federated learning rounds
Author: DECLOUD Team
Requires-Python: >=3.8
Requires-Dist: requests>=2.28.0
Dynamic: author
Dynamic: requires-dist
Dynamic: requires-python
Dynamic: summary
